aioambient/__init__.py
aioambient/api.py
aioambient/api_request_handler.py
aioambient/const.py
aioambient/errors.py
aioambient/open_api.py
aioambient/py.typed
aioambient/util/__init__.py
aioambient/util/climate_utils.py
aioambient/util/location_utils.py
aioambient/websocket.py
aioambient-2024.1.0.dist-info/LICENSE
aioambient-2024.1.0.dist-info/METADATA
aioambient-2024.1.0.dist-info/WHEEL
aioambient-2024.1.0.dist-info/RECORD
