Metadata-Version: 2.1
Name: aioambient
Version: 2024.1.0
Summary: A clean, async-friendly library for the Ambient Weather API
Home-page: https://github.com/bachya/aioambient
License: MIT
Author: Aaron Bach
Author-email: bachya1208@gmail.com
Requires-Python: >=3.10,<4.0
Classifier: License :: OSI Approved :: MIT License
Classifier: Programming Language :: Python
Classifier: Programming Language :: Python :: 3
Classifier: Programming Language :: Python :: 3.10
Classifier: Programming Language :: Python :: 3.11
Classifier: Programming Language :: Python :: 3.12
Classifier: Programming Language :: Python :: Implementation :: CPython
Classifier: Programming Language :: Python :: Implementation :: PyPy
Requires-Dist: aiohttp (>=3.9.0b0)
Requires-Dist: certifi (>=2023.07.22)
Requires-Dist: python-engineio (>=3.13.1,<5.0.0)
Requires-Dist: python-socketio (>=4.6,<6.0)
Requires-Dist: websockets (>=11.0.1)
Requires-Dist: yarl (>=1.9.2)
Project-URL: Bug Tracker, https://github.com/bachya/aioambient/issues
Project-URL: Changelog, https://github.com/bachya/aioambient/releases
Project-URL: Repository, https://github.com/bachya/aioambient
